<?xml version="1.0" encoding="utf-8"?>
<mt_config>
  <language_code>es</language_code>
  <locale_space name="metratech.com/UnbundledDiscount">
    <locale_entry>
      <Name>metratech.com/UnbundledDiscount</Name>
      <Value>Descuentos desglosados</Value>
    </locale_entry>
    <locale_entry>
      <Name>metratech.com/UnbundledDiscount/DiscountAmount</Name>
      <Value>Importe del descuento</Value>
    </locale_entry>
    <locale_entry>
      <Name>metratech.com/UnbundledDiscount/DiscountID</Name>
      <Value>ID del descuento</Value>
    </locale_entry>
    <locale_entry>
      <Name>metratech.com/UnbundledDiscount/DiscountName</Name>
      <Value>Nombre del descuento</Value>
    </locale_entry>
    <locale_entry>
      <Name>metratech.com/UnbundledDiscount/DiscountTaxAmount</Name>
      <Value>Importe de los impuestos del descuento</Value>
    </locale_entry>
  </locale_space>
</mt_config>