<?xml version="1.0" encoding="utf-8"?>
<GridLayout xmlns:xsi="http://www.w3.org/2001/XMLSchema-instance" xmlns:xsd="http://www.w3.org/2001/XMLSchema">
    <Name>EmailedDocumentEntity</Name>
    <Title>
        <Value>Emailed Documents</Value>
    </Title>
    <Exportable>false</Exportable>
    <Height>600</Height>
    <Width>100%</Width>
    <Expandable>false</Expandable>
    <Buttons>Custom</Buttons>
    <DataSourceURL>~/MetraAR/AjaxServices/CopyInvoiceSvc.aspx</DataSourceURL>
    <MultiSelect>false</MultiSelect>
    <SelectionModel>Standard</SelectionModel>
    <TotalProperty>TotalRows</TotalProperty>
    <RootElement>Items</RootElement>
    <PageSize>10</PageSize>
    <Description>EmailedDocumentItem</Description>
    <ExpansionCssClass />
    <ShowFilterPanel>false</ShowFilterPanel>
    <!--
    <FilterInputWidth>220</FilterInputWidth>
    <FilterLabelWidth>75</FilterLabelWidth>
    <FilterColumnWidth>350</FilterColumnWidth>-->
    <ShowTopBar>true</ShowTopBar>
    <ShowBottomBar>false</ShowBottomBar>
    <ShowGridFrame>true</ShowGridFrame>
    <ShowGridHeader>true</ShowGridHeader>
    <ShowColumnHeaders>true</ShowColumnHeaders>
    <NoRecordsText>
        <LocalizationTag>NO_RECORDS_TEXT</LocalizationTag>
        <ResourceClassKey>App_GlobalResources/MetraAR</ResourceClassKey>
    </NoRecordsText>
    <FilterPanelLayout>MultiColumn</FilterPanelLayout>
    <FilterPanelCollapsed>true</FilterPanelCollapsed>
    <EnableColumnConfig>true</EnableColumnConfig>
    <EnableFilterConfig>true</EnableFilterConfig>
    <Resizeable>true</Resizeable>
    <ButtonAlignment>Center</ButtonAlignment>
    <DefaultSortField>EmailDate</DefaultSortField>
    <DefaultSortDirection>Descending</DefaultSortDirection>
    <DisplayCount>true</DisplayCount>
    <SearchOnLoad>false</SearchOnLoad>
    <CustomImplementationFilePath />
    <DataBinder>
        <ServicePath>/MetraNet/AjaxServices/GetData.aspx</ServicePath>
        <OutPropertyName />
        <Operation>__Client</Operation>
    </DataBinder>
    <SubGrid />
    <FilterInputWidth>220</FilterInputWidth>
    <FilterLabelWidth>75</FilterLabelWidth>
    <FilterLabelWrap>None</FilterLabelWrap>
    <FilterColumnWidth>350</FilterColumnWidth>
    <CustomOverrideJavascriptIncludes />
    <Elements>
        <Element>
            <RecordElement>true</RecordElement>
            <AssemblyFilename>D:\MetraTech\RMP\Bin\MetraTech.MetraAR.BO.Entity.dll</AssemblyFilename>
            <ObjectName>MetraTech.MetraAR.BO.Entity.EmailedDocumentEntity</ObjectName>
            <ID>DocumentDate</ID>
            <DataType>Date</DataType>
            <IsIdentity>false</IsIdentity>
            <DataIndex>DocumentDate</DataIndex>
            <IsColumn>true</IsColumn>
            <HeaderText>
                <Value>Doc Date</Value>
            </HeaderText>
            <Formatter />
            <Width>90</Width>
            <Resizeable>true</Resizeable>
            <PreventSortable>false</PreventSortable>
            <Sortable>true</Sortable>
            <ColumnHideable>true</ColumnHideable>
            <DefaultColumn>true</DefaultColumn>
            <Exportable>true</Exportable>
            <ShowInExpander>false</ShowInExpander>
            <Filterable>false</Filterable>
            <FilterHideable>true</FilterHideable>
            <DefaultFilter>true</DefaultFilter>
            <RequiredFilter>false</RequiredFilter>
            <FilterLabel />
            <ElementValue>
                <Value />
            </ElementValue>
            <ElementValue2>
                <Value />
            </ElementValue2>
            <FilterReadOnly>false</FilterReadOnly>
            <DropdownItems />
        </Element>
        <Element>
            <RecordElement>true</RecordElement>
            <AssemblyFilename>D:\MetraTech\RMP\Bin\MetraTech.MetraAR.BO.Entity.dll</AssemblyFilename>
            <ObjectName>MetraTech.MetraAR.BO.Entity.EmailedDocumentEntity</ObjectName>
            <ID>DocumentType</ID>
            <DataType>String</DataType>
            <IsIdentity>false</IsIdentity>
            <DataIndex>DocumentType</DataIndex>
            <IsColumn>true</IsColumn>
            <HeaderText>
                <Value>Doc Type</Value>
            </HeaderText>
            <Formatter />
            <Width>90</Width>
            <Resizeable>true</Resizeable>
            <PreventSortable>false</PreventSortable>
            <Sortable>true</Sortable>
            <ColumnHideable>true</ColumnHideable>
            <DefaultColumn>true</DefaultColumn>
            <Exportable>true</Exportable>
            <ShowInExpander>false</ShowInExpander>
            <Filterable>false</Filterable>
            <FilterHideable>true</FilterHideable>
            <DefaultFilter>false</DefaultFilter>
            <RequiredFilter>false</RequiredFilter>
            <FilterLabel />
            <ElementValue>
                <Value />
            </ElementValue>
            <ElementValue2>
                <Value />
            </ElementValue2>
            <FilterReadOnly>false</FilterReadOnly>
            <DropdownItems />
        </Element>
        <Element>
            <RecordElement>true</RecordElement>
            <AssemblyFilename>D:\MetraTech\RMP\Bin\MetraTech.MetraAR.BO.Entity.dll</AssemblyFilename>
            <ObjectName>MetraTech.MetraAR.BO.Entity.EmailedDocumentEntity</ObjectName>
            <ID>DocumentNbr</ID>
            <DataType>String</DataType>
            <IsIdentity>true</IsIdentity>
            <DataIndex>DocumentNbr</DataIndex>
            <IsColumn>true</IsColumn>
            <HeaderText>
                <Value>Doc Number</Value>
            </HeaderText>
            <Formatter />
            <Width>100</Width>
            <Resizeable>true</Resizeable>
            <PreventSortable>false</PreventSortable>
            <Sortable>true</Sortable>
            <ColumnHideable>true</ColumnHideable>
            <DefaultColumn>true</DefaultColumn>
            <Exportable>true</Exportable>
            <ShowInExpander>false</ShowInExpander>
            <Filterable>false</Filterable>
            <FilterHideable>true</FilterHideable>
            <DefaultFilter>false</DefaultFilter>
            <RequiredFilter>false</RequiredFilter>
            <FilterLabel />
            <ElementValue>
                <Value />
            </ElementValue>
            <ElementValue2>
                <Value />
            </ElementValue2>
            <FilterReadOnly>false</FilterReadOnly>
            <DropdownItems />
        </Element>
        <Element>
            <RecordElement>true</RecordElement>
            <AssemblyFilename>D:\MetraTech\RMP\Bin\MetraTech.MetraAR.BO.Entity.dll</AssemblyFilename>
            <ObjectName>MetraTech.MetraAR.BO.Entity.EmailedDocumentEntity</ObjectName>
            <ID>UserName</ID>
            <DataType>String</DataType>
            <IsIdentity>false</IsIdentity>
            <DataIndex>UserName</DataIndex>
            <IsColumn>true</IsColumn>
            <HeaderText>
                <Value>Emailed By</Value>
            </HeaderText>
            <Formatter />
            <Width>100</Width>
            <Resizeable>true</Resizeable>
            <PreventSortable>false</PreventSortable>
            <Sortable>true</Sortable>
            <ColumnHideable>true</ColumnHideable>
            <DefaultColumn>true</DefaultColumn>
            <Exportable>true</Exportable>
            <ShowInExpander>false</ShowInExpander>
            <Filterable>false</Filterable>
            <FilterHideable>true</FilterHideable>
            <DefaultFilter>false</DefaultFilter>
            <RequiredFilter>false</RequiredFilter>
            <FilterLabel />
            <ElementValue>
                <Value />
            </ElementValue>
            <ElementValue2>
                <Value />
            </ElementValue2>
            <FilterReadOnly>false</FilterReadOnly>
            <DropdownItems />
        </Element>
        <Element>
            <RecordElement>true</RecordElement>
            <AssemblyFilename>D:\MetraTech\RMP\Bin\MetraTech.MetraAR.BO.Entity.dll</AssemblyFilename>
            <ObjectName>MetraTech.MetraAR.BO.Entity.EmailedDocumentEntity</ObjectName>
            <ID>EmailDate</ID>
            <DataType>Date</DataType>
            <IsIdentity>false</IsIdentity>
            <DataIndex>EmailDate</DataIndex>
            <IsColumn>true</IsColumn>
            <HeaderText>
                <Value>Emailed On</Value>
            </HeaderText>
            <Formatter />
            <Width>100</Width>
            <Resizeable>true</Resizeable>
            <PreventSortable>false</PreventSortable>
            <Sortable>true</Sortable>
            <ColumnHideable>true</ColumnHideable>
            <DefaultColumn>true</DefaultColumn>
            <Exportable>true</Exportable>
            <ShowInExpander>false</ShowInExpander>
            <Filterable>false</Filterable>
            <FilterHideable>true</FilterHideable>
            <DefaultFilter>true</DefaultFilter>
            <RequiredFilter>false</RequiredFilter>
            <FilterLabel />
            <ElementValue>
                <Value />
            </ElementValue>
            <ElementValue2>
                <Value />
            </ElementValue2>
            <FilterReadOnly>false</FilterReadOnly>
            <DropdownItems />
        </Element>
        <Element>
            <RecordElement>true</RecordElement>
            <AssemblyFilename>D:\MetraTech\RMP\Bin\MetraTech.MetraAR.BO.Entity.dll</AssemblyFilename>
            <ObjectName>MetraTech.MetraAR.BO.Entity.EmailedDocumentEntity</ObjectName>
            <ID>FromEmail</ID>
            <DataType>String</DataType>
            <IsIdentity>false</IsIdentity>
            <DataIndex>FromEmail</DataIndex>
            <IsColumn>true</IsColumn>
            <HeaderText>
                <Value>From</Value>
            </HeaderText>
            <Formatter />
            <Width>160</Width>
            <Resizeable>true</Resizeable>
            <PreventSortable>false</PreventSortable>
            <Sortable>true</Sortable>
            <ColumnHideable>true</ColumnHideable>
            <DefaultColumn>true</DefaultColumn>
            <Exportable>true</Exportable>
            <ShowInExpander>false</ShowInExpander>
            <Filterable>false</Filterable>
            <FilterHideable>true</FilterHideable>
            <DefaultFilter>false</DefaultFilter>
            <RequiredFilter>false</RequiredFilter>
            <FilterLabel />
            <ElementValue>
                <Value />
            </ElementValue>
            <ElementValue2>
                <Value />
            </ElementValue2>
            <FilterReadOnly>false</FilterReadOnly>
            <DropdownItems />
        </Element>
        <Element>
            <RecordElement>true</RecordElement>
            <AssemblyFilename>D:\MetraTech\RMP\Bin\MetraTech.MetraAR.BO.Entity.dll</AssemblyFilename>
            <ObjectName>MetraTech.MetraAR.BO.Entity.EmailedDocumentEntity</ObjectName>
            <ID>ToEmail</ID>
            <DataType>String</DataType>
            <IsIdentity>false</IsIdentity>
            <DataIndex>ToEmail</DataIndex>
            <IsColumn>true</IsColumn>
            <HeaderText>
                <Value>To</Value>
            </HeaderText>
            <Formatter />
            <Width>160</Width>
            <Resizeable>true</Resizeable>
            <PreventSortable>false</PreventSortable>
            <Sortable>true</Sortable>
            <ColumnHideable>true</ColumnHideable>
            <DefaultColumn>true</DefaultColumn>
            <Exportable>true</Exportable>
            <ShowInExpander>false</ShowInExpander>
            <Filterable>false</Filterable>
            <FilterHideable>true</FilterHideable>
            <DefaultFilter>false</DefaultFilter>
            <RequiredFilter>false</RequiredFilter>
            <FilterLabel />
            <ElementValue>
                <Value />
            </ElementValue>
            <ElementValue2>
                <Value />
            </ElementValue2>
            <FilterReadOnly>false</FilterReadOnly>
            <DropdownItems />
        </Element>
    </Elements>
    <ExpanderTemplate />
    <GridButtons />
    <ToolbarButtons />
</GridLayout>